[
    {
        "id": "_894j6eicf",
        "email": "tema@tema.ru",
        "password": "tema"
    },
    {
        "id": "_b3e3ai3049",
        "email": "tema@tema.ru",
        "password": "154665"
    },
    {
        "id": "_b5hb2g42j",
        "email": "tema@tema.ru",
        "password": "d"
    },
    {
        "id": "_8f8dgf5gg7",
        "email": "tema@tema.ru",
        "password": "d"
    },
    {
        "id": "_i49dh7f792",
        "email": "tema@tema.ru",
        "password": "1"
    },
    {
        "id": "_948if08542",
        "email": "tema@tema.ru",
        "password": "asdf"
    },
    {
        "id": "_2f8ace3b4",
        "email": "",
        "password": "dfg"
    },
    {
        "id": "_c4bd3a3487",
        "email": "tema@tema.ru",
        "password": "dfgdfgdfg"
    },
    {
        "id": "_76gf3igg0e",
        "email": "tema@tema.ru",
        "password": "kdjfgfhfbh"
    }
]